Metadata-Version: 2.1
Name: pydavinci
Version: 0.2.3
Summary: A Davinci Resolve API Wrapper
Home-page: https://github.com/pedrolabonia/pydavinci
Author: Pedro Labonia
Author-email: pedromslabonia@gmail.com
License: UNKNOWN
Platform: UNKNOWN
Classifier: Programming Language :: Python :: 3
Classifier: License :: OSI Approved :: MIT License
Classifier: Operating System :: OS Independent
Requires-Python: ==3.6.*
License-File: LICENSE
Requires-Dist: loguru (==0.6.0)
Requires-Dist: pydantic (==1.9.0)
Requires-Dist: typing-extensions (==4.1.1)
